CHANGELOG.md
LICENSE
MANIFEST.in
README.md
ROADMAP.md
requirements.txt
setup.py
ferry/__init__.py
ferry/install.py
ferry/logging.conf
ferry/options.py
ferry.egg-info/PKG-INFO
ferry.egg-info/SOURCES.txt
ferry.egg-info/dependency_links.txt
ferry.egg-info/entry_points.txt
ferry.egg-info/requires.txt
ferry.egg-info/top_level.txt
ferry/cli/__init__.py
ferry/cli/cli.py
ferry/config/__init__.py
ferry/config/cassandra/__init__.py
ferry/config/cassandra/cassandraclientconfig.py
ferry/config/cassandra/cassandraconfig.py
ferry/config/gluster/__init__.py
ferry/config/gluster/glusterconfig.py
ferry/config/hadoop/__init__.py
ferry/config/hadoop/hadoopclientconfig.py
ferry/config/hadoop/hadoopconfig.py
ferry/config/hadoop/hiveconfig.py
ferry/config/hadoop/metastore.py
ferry/config/mongo/__init__.py
ferry/config/mongo/mongoclientconfig.py
ferry/config/mongo/mongoconfig.py
ferry/config/openmpi/__init__.py
ferry/config/openmpi/mpiclientconfig.py
ferry/config/openmpi/mpiconfig.py
ferry/config/spark/__init__.py
ferry/config/spark/sparkclientconfig.py
ferry/config/spark/sparkconfig.py
ferry/config/system/__init__.py
ferry/config/system/aws.py
ferry/config/system/info.py
ferry/config/titan/__init__.py
ferry/config/titan/titanconfig.py
ferry/data/conf/ferry-aws-example.yaml
ferry/data/conf/ferry-default.yaml
ferry/data/conf/ferry-hp-example.yaml
ferry/data/dockerfiles/cassandra/Dockerfile
ferry/data/dockerfiles/cassandra/startnode
ferry/data/dockerfiles/cassandra-client/Dockerfile
ferry/data/dockerfiles/cassandra-client/gods.json
ferry/data/dockerfiles/cassandra-client/loadgods.groovy
ferry/data/dockerfiles/cassandra-client/naturalgraph.groovy
ferry/data/dockerfiles/cassandra-client/restart01.sh
ferry/data/dockerfiles/cassandra-client/rexexample.sh
ferry/data/dockerfiles/cassandra-client/start01.sh
ferry/data/dockerfiles/cassandra-client/startnode
ferry/data/dockerfiles/cassandra-client/stop10.sh
ferry/data/dockerfiles/cassandra-client/test01.sh
ferry/data/dockerfiles/cassandra-client/testusers.db
ferry/data/dockerfiles/ferry-base/Dockerfile
ferry/data/dockerfiles/ferry-base/halt01.sh
ferry/data/dockerfiles/ferry-base/init01.sh
