Metadata-Version: 1.0
Name: ferry
Version: 0.3.3.4
Summary: Big data development environments using Docker
Home-page: http://ferry.opencore.io
Author: OpenCore LLC
Author-email: jlh@opencore.io
License: Apache License 2.0
Platform: UNKNOWN
